kvq/__init__.py
kvquant-0.0.1.dist-info/LICENSE
kvquant-0.0.1.dist-info/METADATA
kvquant-0.0.1.dist-info/WHEEL
kvquant-0.0.1.dist-info/top_level.txt
kvquant-0.0.1.dist-info/RECORD
