Metadata-Version: 2.2
Name: kvquant
Version: 0.0.1
Summary: More for Keys, Less for Values: Adaptive KV Cache Quantization 🐍🚀🎉🦕
Author-email: Mohsen Hariri <mohsen.hariri@case.edu>
License: GPL-3.0 License
Keywords: Large Language Models,Cache,Quantization,Compression,Optimization
Classifier: Programming Language :: Python :: 3.10
Classifier: License :: OSI Approved :: GNU General Public License v3 or later (GPLv3+)
Classifier: Operating System :: OS Independent
Requires-Python: >=3.10
License-File: LICENSE
Requires-Dist: importlib-metadata; python_version < "3.8"
